bls/__init__.py
bls/scheme.py
bls/utils.py
bls_lib-1.0.1.dist-info/LICENSE
bls_lib-1.0.1.dist-info/METADATA
bls_lib-1.0.1.dist-info/WHEEL
bls_lib-1.0.1.dist-info/top_level.txt
bls_lib-1.0.1.dist-info/RECORD
