Metadata-Version: 2.1
Name: bls-lib
Version: 1.0.1
Summary: A simple Python implementation of threshold BLS signatures.
Home-page: https://pypi.org/project/bls-lib
Author: Alberto Sonnino
Author-email: alberto.sonnino@ucl.ac.uk
License: UNKNOWN
Project-URL: Paper, https://iacr.org/archive/asiacrypt2001/22480516.pdf
Project-URL: Bug Reports, https://github.com/asonnino/bls
Project-URL: Source, https://github.com/asonnino/bls
Keywords: cryptography signatures digital-signatures threhshold-cryptography
Platform: UNKNOWN
Classifier: Development Status :: 3 - Alpha
Classifier: Intended Audience :: Science/Research
Classifier: Topic :: Security :: Cryptography
Classifier: License :: OSI Approved :: GNU General Public License v3 or later (GPLv3+)
Classifier: Programming Language :: Python :: 3.6
